GPS/Make_Annotations_V2.py
GPS/__init__.py
GPS/__main__.py
GPS/cauchy_combination_test.py
GPS/config.py
GPS/find_latent_representation.py
GPS/format_sumstats.py
GPS/generate_ldscore.py
GPS/generate_r2_matrix.py
GPS/jackknife.py
GPS/latent_to_gene.py
GPS/main.py
GPS/make_annotations.py
GPS/regression_read.py
GPS/spatial_ldsc_multiple_sumstats.py
GPS/visualize.py
GPS/GNN_VAE/__init__.py
GPS/GNN_VAE/adjacency_matrix.py
GPS/GNN_VAE/model.py
GPS/GNN_VAE/train.py
gps_mapping-1.60.dist-info/entry_points.txt
gps_mapping-1.60.dist-info/LICENSE
gps_mapping-1.60.dist-info/WHEEL
gps_mapping-1.60.dist-info/METADATA
gps_mapping-1.60.dist-info/RECORD
