Metadata-Version: 2.1
Name: GPS-mapping
Version: 1.60
Summary: Genetics-informed pathogenic spatial mapping
Author-email: liyang <songliyang@westlake.edu.cn>, wenhao <chenwenhao@westlake.edu.cn>
Requires-Python: >=3.8
Classifier: Development Status :: 3 - Alpha
Classifier: Intended Audience :: Developers
Classifier: License :: OSI Approved :: MIT License
Classifier: Programming Language :: Python :: 3.8
Classifier: Programming Language :: Python :: 3.9
Classifier: Operating System :: POSIX :: Linux
Requires-Dist: numpy
Requires-Dist: pandas
Requires-Dist: scipy
Requires-Dist: scikit-learn
Requires-Dist: matplotlib
Requires-Dist: seaborn
Requires-Dist: tqdm
Requires-Dist: progress
Requires-Dist: pyyaml
Requires-Dist: torch
Requires-Dist: torch-geometric
Requires-Dist: pyranges
Requires-Dist: pyfiglet
Requires-Dist: plotly
Requires-Dist: kaleido
Requires-Dist: sphinx ; extra == "doc"
Requires-Dist: sphinx-argparse ; extra == "doc"
Requires-Dist: sphinx-autobuild ; extra == "doc"
Requires-Dist: sphinx-autodoc-typehints ; extra == "doc"
Requires-Dist: sphinx-basic-ng ; extra == "doc"
Requires-Dist: sphinx-charts ; extra == "doc"
Requires-Dist: sphinx-copybutton ; extra == "doc"
Requires-Dist: sphinx_inline_tabs ; extra == "doc"
Requires-Dist: sphinx-markdown-tables ; extra == "doc"
Requires-Dist: sphinx-rtd-theme ; extra == "doc"
Requires-Dist: sphinxcontrib-applehelp ; extra == "doc"
Requires-Dist: sphinxcontrib-devhelp ; extra == "doc"
Requires-Dist: sphinxcontrib-htmlhelp ; extra == "doc"
Requires-Dist: sphinxcontrib-jquery ; extra == "doc"
Requires-Dist: sphinxcontrib-jsmath ; extra == "doc"
Requires-Dist: sphinxcontrib-qthelp ; extra == "doc"
Requires-Dist: sphinxcontrib-serializinghtml ; extra == "doc"
Requires-Dist: furo ; extra == "doc"
Requires-Dist: myst-parser ; extra == "doc"
Requires-Dist: nbsphinx ; extra == "doc"
Project-URL: Documentation, https://...
Project-URL: Home, https://github.com/LeonSong1995/GPS
Project-URL: Website, https://...
Provides-Extra: doc
